fluxture/__init__.py
fluxture/__main__.py
fluxture/async_utils.py
fluxture/bitcoin.py
fluxture/blockchain.py
fluxture/crawl_schema.py
fluxture/crawler.py
fluxture/db.py
fluxture/fluxture.py
fluxture/geolocation.py
fluxture/kml.py
fluxture/messaging.py
fluxture/serialization.py
fluxture/shodan.py
fluxture/statistics.py
fluxture/structures.py
fluxture/topology.py
fluxture-0.0.1.dist-info/LICENSE
fluxture-0.0.1.dist-info/METADATA
fluxture-0.0.1.dist-info/WHEEL
fluxture-0.0.1.dist-info/entry_points.txt
fluxture-0.0.1.dist-info/top_level.txt
fluxture-0.0.1.dist-info/RECORD
